safedb/__init__.py
safedb/database.py
safedb-0.1.0.dist-info/METADATA
safedb-0.1.0.dist-info/WHEEL
safedb-0.1.0.dist-info/RECORD
