Metadata-Version: 2.1
Name: safedb
Version: 0.1.0
Summary: SafeDB is a simple and secure database framework for Python.
Author: BossBoss2011
Author-email: bogdanelsandu@hotmail.com
Requires-Python: >=3.12,<4.0
Classifier: Programming Language :: Python :: 3
Classifier: Programming Language :: Python :: 3.12
